object_colors/__init__.py
object_colors/_version.py
object_colors/py.typed
object_colors-2.3.1.dist-info/LICENSE
object_colors-2.3.1.dist-info/METADATA
object_colors-2.3.1.dist-info/WHEEL
object_colors-2.3.1.dist-info/RECORD
