Metadata-Version: 2.1
Name: object-colors
Version: 2.3.1
Summary: Object-oriented library for stylizing terminal output
Home-page: https://pypi.org/project/object-colors/
License: MIT
Keywords: ansi,color,oop,terminal,tty
Author: jshwi
Author-email: stephen@jshwisolutions.com
Maintainer: jshwi
Maintainer-email: stephen@jshwisolutions.com
Requires-Python: >=3.8,<4.0
Classifier: License :: OSI Approved :: MIT License
Classifier: Programming Language :: Python :: 3
Classifier: Programming Language :: Python :: 3.8
Classifier: Programming Language :: Python :: 3.9
Classifier: Programming Language :: Python :: 3.10
Classifier: Programming Language :: Python :: 3.11
Requires-Dist: colorama (>=0.4.4,<0.5.0)
Project-URL: Documentation, https://object-colors.readthedocs.io/en/latest
Project-URL: Repository, https://github.com/jshwi/object-colors
